CvUse/__init__.py
Cv_Use-1.1.0.dist-info/LICENSE.txt
Cv_Use-1.1.0.dist-info/METADATA
Cv_Use-1.1.0.dist-info/WHEEL
Cv_Use-1.1.0.dist-info/top_level.txt
Cv_Use-1.1.0.dist-info/RECORD
