Metadata-Version: 2.1
Name: Cv-Use
Version: 1.1.0
Summary: This is a self-use, simple, module for operating opencv
Home-page: UNKNOWN
Author: ChenShuai-Zhang
Author-email: aeuna@qq.com
License: UNKNOWN
Platform: UNKNOWN
Classifier: Programming Language :: Python :: 3
Classifier: License :: OSI Approved :: MIT License
Classifier: Operating System :: OS Independent
License-File: LICENSE.txt
